Socketer/__init__.py
Socketer/main.py
Socketer-0.75.dist-info/METADATA
Socketer-0.75.dist-info/WHEEL
Socketer-0.75.dist-info/top_level.txt
Socketer-0.75.dist-info/RECORD
