Metadata-Version: 2.1
Name: Socketer
Version: 0.75
